dfvfs/__init__.py
dfvfs/analyzer/__init__.py
dfvfs/analyzer/analyzer.py
dfvfs/analyzer/analyzer_helper.py
dfvfs/analyzer/apfs_analyzer_helper.py
dfvfs/analyzer/apfs_container_analyzer_helper.py
dfvfs/analyzer/apm_analyzer_helper.py
dfvfs/analyzer/bde_analyzer_helper.py
dfvfs/analyzer/bzip2_analyzer_helper.py
dfvfs/analyzer/cpio_analyzer_helper.py
dfvfs/analyzer/cs_analyzer_helper.py
dfvfs/analyzer/ewf_analyzer_helper.py
dfvfs/analyzer/ext_analyzer_helper.py
dfvfs/analyzer/fat_analyzer_helper.py
dfvfs/analyzer/gpt_analyzer_helper.py
dfvfs/analyzer/gzip_analyzer_helper.py
dfvfs/analyzer/hfs_analyzer_helper.py
dfvfs/analyzer/luksde_analyzer_helper.py
dfvfs/analyzer/lvm_analyzer_helper.py
dfvfs/analyzer/modi_analyzer_helper.py
dfvfs/analyzer/ntfs_analyzer_helper.py
dfvfs/analyzer/phdi_analyzer_helper.py
dfvfs/analyzer/qcow_analyzer_helper.py
dfvfs/analyzer/specification.py
dfvfs/analyzer/tar_analyzer_helper.py
dfvfs/analyzer/tsk_analyzer_helper.py
dfvfs/analyzer/tsk_partition_analyzer_helper.py
dfvfs/analyzer/vhdi_analyzer_helper.py
dfvfs/analyzer/vmdk_analyzer_helper.py
dfvfs/analyzer/vshadow_analyzer_helper.py
dfvfs/analyzer/xfs_analyzer_helper.py
dfvfs/analyzer/xz_analyzer_helper.py
dfvfs/analyzer/zip_analyzer_helper.py
dfvfs/compression/__init__.py
dfvfs/compression/bzip2_decompressor.py
dfvfs/compression/decompressor.py
dfvfs/compression/manager.py
dfvfs/compression/xz_decompressor.py
dfvfs/compression/zlib_decompressor.py
dfvfs/credentials/__init__.py
dfvfs/credentials/apfs_credentials.py
dfvfs/credentials/bde_credentials.py
dfvfs/credentials/credentials.py
dfvfs/credentials/cs_credentials.py
dfvfs/credentials/encrypted_stream_credentials.py
dfvfs/credentials/keychain.py
dfvfs/credentials/luksde_credentials.py
dfvfs/credentials/manager.py
dfvfs/encoding/__init__.py
dfvfs/encoding/base16_decoder.py
dfvfs/encoding/base32_decoder.py
dfvfs/encoding/base64_decoder.py
dfvfs/encoding/decoder.py
dfvfs/encoding/manager.py
dfvfs/encryption/__init__.py
dfvfs-20231208.dist-info/ACKNOWLEDGEMENTS
dfvfs-20231208.dist-info/AUTHORS
dfvfs-20231208.dist-info/LICENSE
dfvfs-20231208.dist-info/METADATA
dfvfs-20231208.dist-info/README
dfvfs-20231208.dist-info/WHEEL
dfvfs-20231208.dist-info/top_level.txt
dfvfs-20231208.dist-info/RECORD
